{"filesize_bytes":42880,"metadata":{"icc:model":"IEC 61966-2.1 Default RGB colour space - sRGB","icc:description":"sRGB IEC61966-2.1","icc:copyright":"Copyright (c) 1998 Hewlett-Packard Company","icc:manufacturer":"IEC http://www.iec.ch","exif:Artist":"Steve Dykes","exif:Copyright":"..2014 Steve Dykes"},"sha1":"b664582dbb187b2dc679ee017b77068a391ddda3","filename":"party_house_for_web.jpg","mimetype":"image/jpeg","url":"frucor.co.nz@@http://www.frucor.co.nz/images/brands/party_house_for_web.jpg"}