{"filesize_bytes":197492,"mimetype":"application/pdf","metadata":{"date":["2011-05-24T17:29:07+12:00","2013-04-02T12:54:23+13:00"],"misc":{"dc_subject":["[]"],"dc_title":["{}"],"dc_contributor":["[]"],"dc_date":["[]"],"dc_language":["[]"],"dc_description":["{}"],"dc_publisher":["[]"],"cache":["{}"],"dc_relation":["[]"],"dc_type":["[]"],"dc_creator":["[]"],"dc_rights":["{}"],"custom_properties":["{}"]},"software":["Adobe InDesign CS3 (5.0)","Adobe PDF Library 8.0"]},"filename":"PG-Young%20People-110419.pdf","sha1":"88c963c37af9bd176fe8d932387f47457d21a49e","children":[{"date":[]}],"url":"hpa.org.nz@@http://www.hpa.org.nz/sites/default/files/PG-Young%20People-110419.pdf"}