{"filesize_bytes":23736,"sha1":"8b3061ae641e389dcbe87bb8ba0c87f63d6d86c6","metadata":{"misc":{"exif:Software":["Google"],"exif:thumbnail:InteroperabilityIndex":["R98"],"exif:thumbnail:InteroperabilityVersion":["48, 49, 48, 48"]},"ascii":{"exif:thumbnail:InteroperabilityVersion->ASCII":["0100"]},"date":["2016-07-05T19:03:20"]},"filename":"imp_willkommen.jpg","mimetype":"image/jpeg","url":"taxjustice.blogspot.co.nz@@http://1.bp.blogspot.com/-rjkFqKS8Eow/UkLjB3PI7LI/AAAAAAAAEiU/bcdhEnMN4_g/s1600/imp_willkommen.jpg"}