{"mimetype":"text/html","metadata":{"/span":"","/li":"","/script":"www.taxjustice.net/about/who-we-are/\" target=\"_blank\" >TJN","/p":"","span":" external debts are less than $200 billion. So Africa is a major net creditor","/a":" trillion of private financial wealth is located, untaxed or lightly taxed, in secrecy jurisdictions around the world. Secrecy jurisdictions - a term we ","a":"over $1 trillion"},"filename":"Luxembourg.pdf","sha1":"035066aab1dccc89d439a49dae78ccbc9d493025","filesize_bytes":18797,"url":"taxjustice.blogspot.co.nz@@http://www.secrecyjurisdictions.com/PDF/Luxembourg.pdf"}